rosteron/__init__.py
rosteron/exceptions.py
rosteron-1.0.0.dist-info/LICENSE
rosteron-1.0.0.dist-info/METADATA
rosteron-1.0.0.dist-info/WHEEL
rosteron-1.0.0.dist-info/top_level.txt
rosteron-1.0.0.dist-info/RECORD
