Metadata-Version: 2.1
Name: rosteron
Version: 1.0.0
Summary: Read-only RosterOn Mobile roster access
Home-page: https://github.com/Lx/python-rosteron
Author: Alex Peters
License: UNKNOWN
Platform: UNKNOWN
Classifier: Development Status :: 5 - Production/Stable
Classifier: License :: OSI Approved :: MIT License
Classifier: Natural Language :: English
Classifier: Operating System :: OS Independent
Classifier: Programming Language :: Python :: 3.7
Classifier: Typing :: Typed
Requires-Python: ~=3.7
Requires-Dist: attrs
Requires-Dist: beautifulsoup4
Requires-Dist: mechanicalsoup
